pycolorecho/__init__.py
pycolorecho/__main__.py
pycolorecho-0.1.1.dist-info/LICENSE
pycolorecho-0.1.1.dist-info/METADATA
pycolorecho-0.1.1.dist-info/WHEEL
pycolorecho-0.1.1.dist-info/top_level.txt
pycolorecho-0.1.1.dist-info/RECORD
