Metadata-Version: 2.1
Name: pycolorecho
Version: 0.1.1
Summary: Simple Python package for colorized terminal output
Home-page: https://github.com/coldsofttech/pycolorecho
Author: coldsofttech
License: MIT
Keywords: color,text-color,text-background-color,text-effect,text-case,terminal,colorization,style,text
Classifier: Development Status :: 4 - Beta
Classifier: Intended Audience :: Developers
Classifier: Topic :: Software Development :: Libraries :: Python Modules
Classifier: Topic :: Utilities
Classifier: License :: OSI Approved :: MIT License
Classifier: Programming Language :: Python :: 3.10
Classifier: Programming Language :: Python :: 3.11
Classifier: Programming Language :: Python :: 3.12
License-File: LICENSE
